{
  "lastChecked": "2026-06-18T22:28:15.959Z",
  "notices": [
    {
      "date": "2026-06-09",
      "title": "Notice regarding Publication of 2nd Merit List for Admission into FYUGP (B.A) offered by PDUAM, Amjonga",
      "url": "https://pduamamjonga.ac.in/files/6699-20260609215154.pdf",
      "hash": "f5e739cd2264cf77973b10109e621562654b1f76da9a539a759323b96de32a3d",
      "detected_at": "2026-06-09T18:33:04.209Z"
    },
    {
      "date": "2026-06-09",
      "title": "Notice regarding Publication of 2nd Merit List for Admission into FYUGP (B.Sc.) offered by PDUAM, Amjonga",
      "url": "https://pduamamjonga.ac.in/files/6522-20260609215111.pdf",
      "hash": "22ac253b5f384989b67f5521120cc089540466c5d620bc8c36cda5488c689029",
      "detected_at": "2026-06-09T18:33:04.209Z"
    },
    {
      "date": "2026-06-03",
      "title": "Merit List for admission into BA First semester (2026-27)",
      "url": "https://pduamamjonga.ac.in/files/8354-20260603110417.pdf",
      "hash": "1826a4f00422e3a7b1328fdef34ded5d9645dda44adb9cb2e793509b4ccafdd3",
      "detected_at": "2026-06-03T16:03:18.657Z"
    },
    {
      "date": "2026-06-03",
      "title": "Merit List for admission into BSc First semester (2026-27)",
      "url": "https://pduamamjonga.ac.in/files/8875-20260603110320.pdf",
      "hash": "5d997f577adf87b9b4ba42a9b89ba432d1a9c4a3d85aaaab29ba3a51ce7443e8",
      "detected_at": "2026-06-03T16:03:18.657Z"
    },
    {
      "date": "2026-06-02",
      "title": "Admission Notice for B.A/ B.Sc. 1st Semester ( FYUGP) 2026-27",
      "url": "https://pduamamjonga.ac.in/files/1557-20260603125003. 1 Sem 2026",
      "hash": "6a3c6cce3a0ba1b7c289e1ce878b84f5397440a0fcdcd16ed5c624469a3a0140",
      "detected_at": "2026-06-03T16:03:18.657Z"
    },
    {
      "date": "2026-05-30",
      "title": "BA/BSc - II & IV Semester (Arrear Batch 2023 & 2024) Examination Notice",
      "url": "https://pduamamjonga.ac.in/files/8550-20260530140842.pdf",
      "hash": "8a0ed37d6999ddfd7d2a2239187272a6966bf764bb41f2d2ac3d4174a2ee2891",
      "detected_at": "2026-05-30T08:43:02.697Z"
    },
    {
      "date": "2026-05-20",
      "title": "HS Second Year Re-Admission notice for the academic session 2026-27 for those students who were unsuccessful in the HS Final Year Examination 2026",
      "url": "https://pduamamjonga.ac.in/files/6149-20260521144710.pdf",
      "hash": "d270be263fdffd9f0ef4167fff52ed531b1e95ad38b6da84d6c0fbe374b925a5",
      "detected_at": "2026-05-21T11:56:50.873Z"
    },
    {
      "date": "2026-05-18",
      "title": "FYUGP (BA & BSc) First Semester Admission notice for the academic session 2026-27",
      "url": "https://pduamamjonga.ac.in/files/9601-20260521144521.pdf",
      "hash": "b83cbcaef9f8494d8e7b53e74df2d086950c3b072116cf7c9ecf53ec530c0de6",
      "detected_at": "2026-05-21T11:56:50.873Z"
    },
    {
      "date": "2026-05-15",
      "title": "Notice regarding start of classes of HS First year for the academic session 2026-27",
      "url": "https://pduamamjonga.ac.in/files/9457-20260515171242.pdf",
      "hash": "69856d12a18f3a02873d819f0600b10addcf4e0a37fb94c7d66b4aef8b8861f2",
      "detected_at": "2026-05-18T17:57:15.298Z"
    },
    {
      "date": "2026-05-12",
      "title": "Notice regarding BA & BSc Fourth semester Examination 2026",
      "url": "https://pduamamjonga.ac.in/files/5673-20260515171036.pdf",
      "hash": "5d6f50e096426bf36329c58bfe30410ae5a8d59cd04d776ea4449dc5d4b87a6d",
      "detected_at": "2026-05-18T17:57:15.298Z"
    },
    {
      "date": "2026-05-05",
      "title": "Merit list-2 for admission into HS First Year (Arts Stream) for the academic session 2026-27",
      "url": "https://pduamamjonga.ac.in/files/3749-20260505170722.pdf",
      "hash": "8e20384ab7a4a4bfc269c3b91be7b0c0ebbaa71303253eaee5c0ab6d04408c20",
      "detected_at": "2026-05-18T17:57:15.298Z"
    },
    {
      "date": "2026-05-05",
      "title": "Merit list-2 for admission into HS First Year (Science Stream) for the academic session 2026-27",
      "url": "https://pduamamjonga.ac.in/files/6563-20260505162905.pdf",
      "hash": "09a5612ffbf51cc254767dd80f38fe2472662f3927b0297f012985b47d094dc0",
      "detected_at": "2026-05-18T17:57:15.298Z"
    },
    {
      "date": "2026-04-28",
      "title": "Examination Form Fill up notice for UG (BA&BSc) Sixth Semester 2025-26",
      "url": "https://pduamamjonga.ac.in/files/7620-20260428171244.pdf",
      "hash": "9cd837ff23f3818cbcb614f15db28b8c2b17e73adb542d6ccc45e19d7b771ebc",
      "detected_at": "2026-05-18T17:57:15.298Z"
    },
    {
      "date": "2026-04-28",
      "title": "Examination Form Fill up notice for UG (BA&BSc) Second Semester 2025-26",
      "url": "https://pduamamjonga.ac.in/files/7272-20260428171112.pdf",
      "hash": "bcedb5ed44f57ddc4aadb3bc432c0b38b2bfe361a65d3d9b72949bf2768600fc",
      "detected_at": "2026-05-18T17:57:15.298Z"
    },
    {
      "date": "2026-04-25",
      "title": "Merit List for admission into the classes of Higher Secondary First Year (Science) for the academic session 2026-27",
      "url": "https://pduamamjonga.ac.in/files/9931-20260425111429.pdf",
      "hash": "5ba0333942a29c39886659394ae89afc429cd87be80206d05d4d9f14ef858127",
      "detected_at": "2026-05-18T17:57:15.298Z"
    },
    {
      "date": "2026-04-25",
      "title": "Merit List for admission into the classes of Higher Secondary First Year (Arts) for the academic session 2026-27",
      "url": "https://pduamamjonga.ac.in/files/5042-20260425111351.pdf",
      "hash": "4d15d87eda0b9f76e674d7c411fb839194d625d83b64947b13bf90be691ec74b",
      "detected_at": "2026-05-18T17:57:15.298Z"
    },
    {
      "date": "2026-04-24",
      "title": "Notice regarding prohibition of use of mobile phones and loitering in the college campus",
      "url": "https://pduamamjonga.ac.in/files/2759-20260425094405.pdf",
      "hash": "02c9388ba7fcca095a8731618cd9af1fd3b2489ad6a310e9f277b999a4e4cc4d",
      "detected_at": "2026-05-18T17:57:15.298Z"
    },
    {
      "date": "2026-04-23",
      "title": "Notice regarding commencement of regular classes of H. S. 2nd Year Arts Stream & Science stream",
      "url": "https://pduamamjonga.ac.in/files/8796-20260425094558.pdf",
      "hash": "97dbfe6a74679930b1fc18b7c704084b23f65e0e4b0bf0de44fe0a9e4322037a",
      "detected_at": "2026-05-18T17:57:15.298Z"
    },
    {
      "date": "2026-04-18",
      "title": "Programs for Sessional Examination 2025-26 (Even Semester)",
      "url": "https://pduamamjonga.ac.in/files/1601-20260420131851.pdf",
      "hash": "8cf2ec17a76e3ec685fafc91472c2aeb6c96904008e15051cf3bf0e2f4988341",
      "detected_at": "2026-05-18T17:57:15.298Z"
    },
    {
      "date": "2026-04-11",
      "title": "Notification for Admission HS 1st Year Students (Arts Stream & Science Stream) for the session 2026-27",
      "url": "https://pduamamjonga.ac.in/files/3351-20260413134128.pdf",
      "hash": "c06ed547482d506c84fbed5c7c64edcf9de24e8ad1136b6e380fc29bfb149119",
      "detected_at": "2026-05-18T17:57:15.298Z"
    },
    {
      "date": "2026-02-25",
      "title": "notice regarding live streaming of the ceremonial launching programme of the scheme Mukhya Mantrir Nijut Babu Aasoni (MMNBA)",
      "url": "https://pduamamjonga.ac.in/files/8116-20260225115403.pdf",
      "hash": "7ab8abc1d6d5b57c92e987474d289a92abbf335760d7fd71f0ecaea0294504b6",
      "detected_at": "2026-05-18T17:57:15.298Z"
    },
    {
      "date": "2026-02-05",
      "title": "Form Fill Up Notice for HS First Year Examination 2026",
      "url": "https://pduamamjonga.ac.in/files/6815-20260205161522.pdf",
      "hash": "5c4b307d627990510c0dc16eee656e4779d38881ac4ba529ef3d6475c81ba3e8",
      "detected_at": "2026-05-18T17:57:15.298Z"
    },
    {
      "date": "2026-01-24",
      "title": "Programme of HS 1st year Final Examination 2026",
      "url": "https://pduamamjonga.ac.in/files/4104-20260127213605.pdf",
      "hash": "c5b7a3689958e0ea9481af100046b06e59e4c2d3d128f94e29d6d9b09214c67e",
      "detected_at": "2026-05-18T17:57:15.298Z"
    },
    {
      "date": "2026-01-24",
      "title": "HS FINAL EXAMINATION 2026 PRACTICAL GROUP DISTRIBUTION",
      "url": "https://pduamamjonga.ac.in/files/1918-20260127212522.pdf",
      "hash": "2ddbe602ef87413bf262c9372273fcdbf5e835dd8c4f991f734a6d40bba5d815",
      "detected_at": "2026-05-18T17:57:15.298Z"
    },
    {
      "date": "2026-01-21",
      "title": "SEC EXAMINATION PROGRAMME",
      "url": "https://pduamamjonga.ac.in/files/9947-20260127212412.pdf",
      "hash": "d6ed5e236b912f2d6a6f84de2acfeccf515c6bf296632328aaab2887a0266173",
      "detected_at": "2026-05-18T17:57:15.298Z"
    },
    {
      "date": "2026-01-05",
      "title": "EXAMINATION NOTICE BA/B.SC 1 ST SEMESTER (ARREAR-2024)",
      "url": "https://pduamamjonga.ac.in/files/9364-20260127212211.pdf",
      "hash": "98bff32125928891c4edc26275b70ebe75c55cc3aa2cb81168141c23757e74da",
      "detected_at": "2026-05-18T17:57:15.298Z"
    },
    {
      "date": "2026-01-01",
      "title": "Programme HS Final Examination-2026",
      "url": "https://pduamamjonga.ac.in/files/5424-20260127211840.pdf",
      "hash": "32670fc724d0832c5d453bb8c6c5ee5114fe74daf9226157cdb5d4f25fbc0d2f",
      "detected_at": "2026-05-18T17:57:15.298Z"
    },
    {
      "date": "2025-12-09",
      "title": "Interview Notice Department of Bodo",
      "url": "https://pduamamjonga.ac.in/files/7420-20251209165947.pdf",
      "hash": "4b4cd12d2cf56c5bad6a90780f49f7ccb28258c138784f87c79d086ed57b64b8",
      "detected_at": "2026-05-18T17:57:15.298Z"
    },
    {
      "date": "2025-12-08",
      "title": "Corrigendum Notice",
      "url": "https://pduamamjonga.ac.in/files/9782-20251208132155.pdf",
      "hash": "e0baa5f019b41db32394f1fa2ae080436eddd1e06a1ac36cc94bc197b0b43521",
      "detected_at": "2026-05-18T17:57:15.298Z"
    },
    {
      "date": "2025-11-20",
      "title": "Accepted List of Assistant Professors in the Department of Bodo, PDUAM, Amjonga",
      "url": "https://pduamamjonga.ac.in/files/1631-20251122200525.pdf",
      "hash": "b40513a74c7e1bae97369e78f6383fffe6fbc7ec9af51d809f59f6d04fdf6243",
      "detected_at": "2026-05-18T17:57:15.298Z"
    },
    {
      "date": "2025-11-20",
      "title": "Rejection list of Bodo Applicants",
      "url": "https://pduamamjonga.ac.in/files/6765-20251122200201.pdf",
      "hash": "50d0a1ed4d78d39ed68044dcc30c30688ac571e65b09f0171a9099a9b1bac1bf",
      "detected_at": "2026-05-18T17:57:15.298Z"
    },
    {
      "date": "2025-11-11",
      "title": "Winner list of Students' Union Election 2025-26",
      "url": "https://pduamamjonga.ac.in/files/2854-20251111155030.jpg",
      "hash": "316c5912c85505dd3e34c609c26819e8381e361c4ebb1883b1f7e7203c715325",
      "detected_at": "2026-05-18T17:57:15.298Z"
    },
    {
      "date": "2025-11-04",
      "title": "Notice for Students Election 2025-26 FINAL LIST OF CONTESTING CANDIDATES:",
      "url": "https://pduamamjonga.ac.in/files/8444-20251104150201.pdf",
      "hash": "374fd5390db72be2809e33dc08c7df972fa12165ba98b9ece0eaaa4b09306af3",
      "detected_at": "2026-05-18T17:57:15.298Z"
    },
    {
      "date": "2025-11-03",
      "title": "Notification for Students Union Election, 2025-26",
      "url": "https://pduamamjonga.ac.in/files/9940-20251103151603.pdf",
      "hash": "c46dd003f2ebc680e3e91de71a2e85f6234f14d776925568e214c895157d9952",
      "detected_at": "2026-05-18T17:57:15.298Z"
    },
    {
      "date": "2025-10-29",
      "title": "Notification for Code of Conduct Students' Election 2025-26",
      "url": "https://pduamamjonga.ac.in/files/4836-20251029113240.pdf",
      "hash": "c8a4715e1f113cfc10a0a84b22de8b0470ac7b75c8b82ddbbd3c992b319f4395",
      "detected_at": "2026-05-18T17:57:15.298Z"
    },
    {
      "date": "2025-10-25",
      "title": "Notice regarding distribution of cheque to the girl students studying in the classes of XI, XII, UG-First Year & UG-Second Year under PDUAM, Amjonga for the academic session 2025-26 in connection with the Mukhya Mantrir Nijiut Moina Asoni 2.0",
      "url": "https://pduamamjonga.ac.in/files/6020-20251025143128.pdf",
      "hash": "238c8f4c0be41e2ee4d3fd594dc3645ac7fb27e57d6216860fb8c50308adad2e",
      "detected_at": "2026-05-18T17:57:15.298Z"
    },
    {
      "date": "2025-10-23",
      "title": "Holiday Notice on 28/10/2025",
      "url": "https://pduamamjonga.ac.in/files/6259-20251023163623.png",
      "hash": "f020cc0a84bb6254c8f133ecb7489d2644e2ae0b7b4b85f9ecbce25064c7e707",
      "detected_at": "2026-05-18T17:57:15.298Z"
    },
    {
      "date": "2025-10-14",
      "title": "Undertaking for the Post of Assistant Professors in the Deptt. of Bodo PDUAM, Amjonga",
      "url": "https://pduamamjonga.ac.in/files/7706-20251014144345.pdf",
      "hash": "f3e3379dcc17639c636dd5c58d5c59312b44124ec26f93ebce2e18e88f325006",
      "detected_at": "2026-05-18T17:57:15.298Z"
    },
    {
      "date": "2025-10-14",
      "title": "Applications received for the Post of Assistant Professors in the Deptt. of Bodo PDUAM, Amjonga",
      "url": "https://pduamamjonga.ac.in/files/6924-20251014144237.pdf",
      "hash": "31164beac6a617291d49697e46996debe54281c55e14bd764d7d21e37a22399c",
      "detected_at": "2026-05-18T17:57:15.298Z"
    },
    {
      "date": "2025-10-10",
      "title": "Notice regarding BSc Semester I, III & V Arrear Examination for the Batch ( CBCS - 2020 & 2021)",
      "url": "https://pduamamjonga.ac.in/files/7012-20251010160744.pdf",
      "hash": "a887dfe94bc72b26fa5cd1f5a0df099d5c0970f920b6896ea10b7919224536f7",
      "detected_at": "2026-05-18T17:57:15.298Z"
    },
    {
      "date": "2025-09-16",
      "title": "Tender Application Form",
      "url": "https://pduamamjonga.ac.in/files/8290-20250916165358.pdf",
      "hash": "f59e88d1d51d1a9df39639239be173195193d742cddebaa3d715264d9e6f4d60",
      "detected_at": "2026-05-18T17:57:15.298Z"
    },
    {
      "date": "2025-09-16",
      "title": "College Canteen Tender Date Extension Notification",
      "url": "https://pduamamjonga.ac.in/files/1259-20250916165321.pdf",
      "hash": "ac65197600e054b19486e0cced37bc41ce76c2b8fecfd317557a65e402edd0fe",
      "detected_at": "2026-05-18T17:57:15.298Z"
    },
    {
      "date": "2025-09-12",
      "title": "Advertisement Notice: Recruitment of Assistant Professors in Department of Bodo at PDUAM, Amjonga",
      "url": "https://pduamamjonga.ac.in/files/6953-20250912164815.pdf",
      "hash": "acd3fcc21eddb370eda6bfbbb6e0209f4cb55147a4bbe959f3f216b0e59b6cfa",
      "detected_at": "2026-05-18T17:57:15.298Z"
    },
    {
      "date": "2025-09-10",
      "title": "Notice for Lecture Series on IoT in Helthcare organised by Department of Computer Science",
      "url": "https://pduamamjonga.ac.in/files/8679-20250911134206.jpg",
      "hash": "f331ed001a695b37a6c1c5cf57a360c560c45761a1101c11a9086f245d91a52f",
      "detected_at": "2026-05-18T17:57:15.298Z"
    },
    {
      "date": "2025-09-09",
      "title": "Notice for B.A/B.Sc. 1st Semester Library Orentation Programme on 11-09-2025",
      "url": "https://pduamamjonga.ac.in/files/2309-20250911133732.jpg",
      "hash": "81dabae3ec126a4de9d0b7ef84102663d5766bbce167910ba91f361f903f70f3",
      "detected_at": "2026-05-18T17:57:15.298Z"
    },
    {
      "date": "2025-09-09",
      "title": "Notice for Inviting Tender ( College Canteen)",
      "url": "https://pduamamjonga.ac.in/files/3781-20250909153250.pdf",
      "hash": "8bc40cc05fadee460d16c597e0960e6848bf04d9969d45d74002399b5c289efd",
      "detected_at": "2026-05-18T17:57:15.298Z"
    },
    {
      "date": "2025-09-09",
      "title": "Tender Application ( College Canteen)",
      "url": "https://pduamamjonga.ac.in/files/8398-20250909153427.pdf",
      "hash": "b04dc94a93c9a2c31ed4a3b45bf1486fc2f379edf4f1625f1fb9f1ed47f508bb",
      "detected_at": "2026-05-18T17:57:15.298Z"
    },
    {
      "date": "2025-08-28",
      "title": "Tender Application (Assamese)",
      "url": "https://pduamamjonga.ac.in/files/7151-20250828160650.pdf",
      "hash": "f69c5195b6261871f3844f0fa5bf5f090e7bff2c9a010dbc819a30025891e11b",
      "detected_at": "2026-05-18T17:57:15.298Z"
    },
    {
      "date": "2025-08-28",
      "title": "Tender Application",
      "url": "https://pduamamjonga.ac.in/files/8952-20250828160617.pdf",
      "hash": "7a931a3b481ea800e11e245602735f1d5df0dfda396e93badba1a4ada19ddc54",
      "detected_at": "2026-05-18T17:57:15.298Z"
    },
    {
      "date": "2025-08-28",
      "title": "Notice Inviting Tender ( College Canteen)",
      "url": "https://pduamamjonga.ac.in/files/1867-20250828160210.pdf",
      "hash": "e36e2a6763fccf468cb340f1d0f94c612bce9a9493a16df3bb0177fde7b25601",
      "detected_at": "2026-05-18T17:57:15.298Z"
    },
    {
      "date": "2025-08-08",
      "title": "Notice for B.A/B. Sc. Library Orientation Programme from 11th to 18th August, 2025",
      "url": "https://pduamamjonga.ac.in/files/6939-20250809093645.jpg",
      "hash": "3881a6a4062bed95cd64c8ceed14f0f15b1fcd9b83d29a18e428f0480721b497",
      "detected_at": "2026-05-18T17:57:15.298Z"
    },
    {
      "date": "2025-08-05",
      "title": "Notice for HS & BA./B.Sc. Students Mukhya Mantri Nijut Maina Asoni 2.0",
      "url": "https://pduamamjonga.ac.in/files/2359-20250805143333.pdf",
      "hash": "3626dfde88ec59ff9b17065c55f0c2b26706a323495c0d3edd56bed1e0afa59a",
      "detected_at": "2026-05-18T17:57:15.298Z"
    },
    {
      "date": "2025-07-04",
      "title": "Hostel Admission Notice for Girls students of HS, BA & BSc for academic session 2025-26",
      "url": "https://pduamamjonga.ac.in/files/5262-20250704142518.pdf",
      "hash": "19eba15edf87e2fbfe6556904c8fc873ba3e590f1ed08f1752a73cfeed493cce",
      "detected_at": "2026-05-18T17:57:15.298Z"
    },
    {
      "date": "2025-06-17",
      "title": "Notice for Identity card and Uniform Badge for H.S 1st year and B.A/B.Sc. 1st semester 2025",
      "url": "https://pduamamjonga.ac.in/files/8964-20250622135800.pdf",
      "hash": "4a4dabfe0377044e39edafcb61898ef72b9f7956c437959b5b2128e7b2e95859",
      "detected_at": "2026-05-18T17:57:15.298Z"
    },
    {
      "date": "2025-06-16",
      "title": "Notice : Admission for Amtron Internship programme",
      "url": "https://pduamamjonga.ac.in/files/4648-20250622135643.pdf",
      "hash": "4c3b74cd2e79b4960ee27a7a9cf58d8992ec11d9767d414ba569c0f0be233388",
      "detected_at": "2026-05-18T17:57:15.298Z"
    },
    {
      "date": "2025-06-12",
      "title": "Second Merit List BA First Semester FYUGP 2025-26",
      "url": "https://pduamamjonga.ac.in/files/1409-20250612213305.pdf",
      "hash": "a41ba5462274dcee48621823b1c79b1468522f965e38ba3633e6e5cdeb120738",
      "detected_at": "2026-05-18T17:57:15.298Z"
    },
    {
      "date": "2025-06-12",
      "title": "Second Merit List BSc First Semester FYUGP 2025-26",
      "url": "https://pduamamjonga.ac.in/files/3105-20250612213231.pdf",
      "hash": "8cdaf7018dcceb9d07559b7c434f79d1bbd8673915436840b8457978aad889c2",
      "detected_at": "2026-05-18T17:57:15.298Z"
    },
    {
      "date": "2025-06-04",
      "title": "Notice 4th Semester Examination ,2025 re-schedule on 01-07-2025",
      "url": "https://pduamamjonga.ac.in/files/1658-20250604141708.pdf",
      "hash": "d4d8a827bd9c98dd8fc5fac03be8f4c1ee0f679ac9e3d94fa00872177b3f6d10",
      "detected_at": "2026-05-18T17:57:15.298Z"
    },
    {
      "date": "2025-06-04",
      "title": "Notice 4th Semester Examination ,2025 re-schedule on 01-07-2025",
      "url": "https://pduamamjonga.ac.in/files/6956-20250604141644.pdf",
      "hash": "221b099b09f43c30ac5ad6ac7320e7a3d9c6743eac7a85bc870259d8b1918d12",
      "detected_at": "2026-05-18T17:57:15.298Z"
    },
    {
      "date": "2025-06-03",
      "title": "Re-schedule Programme B.A/B.Sc. 2nd Semester Examination 2025",
      "url": "https://pduamamjonga.ac.in/files/4297-20250603131005.pdf",
      "hash": "c1b762112f86d157aae8d6b5fab3134c109f40b14325d0ad06f810d710a0c3f6",
      "detected_at": "2026-05-18T17:57:15.298Z"
    },
    {
      "date": "2025-06-02",
      "title": "First merit list of BSc First Semester for the academic year 2025-26",
      "url": "https://pduamamjonga.ac.in/files/2725-20250602181118.pdf",
      "hash": "92cd10c58fb083c36f647a682df838f74fc0b202d27c273cf0f9719ac7e6a2ba",
      "detected_at": "2026-05-18T17:57:15.298Z"
    },
    {
      "date": "2025-06-02",
      "title": "First merit list of BA First semester for the academic year 2025-26",
      "url": "https://pduamamjonga.ac.in/files/9432-20250602180954.pdf",
      "hash": "557ace5e04e14b6997e2f668ab341f42ea2b3b7a69ab2df79d8a5888ea30c442",
      "detected_at": "2026-05-18T17:57:15.298Z"
    },
    {
      "date": "2025-05-24",
      "title": "Notice for MRG Girls Hostel, PDUAM, Amjonga",
      "url": "https://pduamamjonga.ac.in/files/3536-20250524130934.pdf",
      "hash": "d5847d61771ce2cab1a56f95f0ae7c258880e56d468cc23399f52667ac9c26df",
      "detected_at": "2026-05-18T17:57:15.298Z"
    },
    {
      "date": "2025-05-24",
      "title": "Programme for B.A /B.Sc. 4th Semester Examination, 2025",
      "url": "https://pduamamjonga.ac.in/files/2054-20250524125852.pdf",
      "hash": "d3b3ad1f71a0b52d3699aa819aa13066435ba7d392aabda82d08b2656302aa4e",
      "detected_at": "2026-05-18T17:57:15.298Z"
    },
    {
      "date": "2025-05-22",
      "title": "Admission Notice-cum-Second Provisional Merit List for HS First Year (Arts) for the Academic Year 2025-26",
      "url": "https://pduamamjonga.ac.in/files/9718-20250522133517.pdf",
      "hash": "ff59d475cb271b12b36782f344e35cd6bfdbbf66e5f632a1f09361a4ba19885b",
      "detected_at": "2026-05-18T17:57:15.298Z"
    },
    {
      "date": "2025-05-20",
      "title": "Admission Notice for HS First Year (Science) for the Academic Year 2025-26",
      "url": "https://pduamamjonga.ac.in/files/6241-20250520140007.pdf",
      "hash": "1ffc5b0bd6eddfb5e5f2367ca7fccd806fe64697129f80a0a0f6e2280453ee87",
      "detected_at": "2026-05-18T17:57:15.298Z"
    },
    {
      "date": "2025-05-08",
      "title": "Admission Notice for FYUGP First semester for academic year 2025-26",
      "url": "https://pduamamjonga.ac.in/files/5423-20250508154023.pdf",
      "hash": "1604db6cdb6874deffd562b9c542a96a0d106a60aee0a6bf8a8f9680eff2ad2d",
      "detected_at": "2026-05-18T17:57:15.298Z"
    },
    {
      "date": "2025-05-08",
      "title": "Admission Notice & Provisional Merit List of HS First Year Arts 2025-26",
      "url": "https://pduamamjonga.ac.in/files/7057-20250508152709.pdf",
      "hash": "62aadbe6ff4d99af0c714a50480189102a06c0c4fcaf49bfbe5e50a9d797d330",
      "detected_at": "2026-05-18T17:57:15.298Z"
    },
    {
      "date": "2025-04-28",
      "title": "Provisional Merit List of HS First Year Arts 2025-26",
      "url": "https://pduamamjonga.ac.in/files/7687-20250428151132.pdf",
      "hash": "e102671ca7f400dbec6c3bd8af894522f4393df260cf8436888833591bb8fc97",
      "detected_at": "2026-05-18T17:57:15.298Z"
    },
    {
      "date": "2025-04-28",
      "title": "Provisional Merit List of HS First Year Science 2025-26",
      "url": "https://pduamamjonga.ac.in/files/8138-20250428151109.pdf",
      "hash": "aad4278be5adf2edf1d1bb591ccfd8c6eba318b4658647d987b5c9f9aed0adb6",
      "detected_at": "2026-05-18T17:57:15.298Z"
    },
    {
      "date": "2025-04-24",
      "title": "Revised Programme BA & B.Sc. SIX Semester ( CBCS) Regular & Arrear Examination,2025",
      "url": "https://pduamamjonga.ac.in/files/3467-20250501210235.pdf",
      "hash": "101e85bfbbbb16e3c38de672468596dc4d226ef35439f518cfac681df46b75fe",
      "detected_at": "2026-05-18T17:57:15.298Z"
    },
    {
      "date": "2025-04-24",
      "title": "Revised Programme FYUGP/BA & B.Sc. Second Semester (Regular & Arrear )Examination,2025",
      "url": "https://pduamamjonga.ac.in/files/4986-20250501205801.pdf",
      "hash": "3cd034a3aa23b5924e19c6122b1cb9d2c737e3a77fd7f5dc0007aa4629d5f047",
      "detected_at": "2026-05-18T17:57:15.298Z"
    },
    {
      "date": "2025-04-22",
      "title": "Examination Notice for BA/B.Sc. II Semester & VI semester Arrear Batch Examination 2025",
      "url": "https://pduamamjonga.ac.in/files/3423-20250422210601.pdf",
      "hash": "a8e6f1d1ce61a2914a05e26e2ae87c8bfe5bf732783c40f030b84a7b3fee71dd",
      "detected_at": "2026-05-18T17:57:15.298Z"
    },
    {
      "date": "2025-04-22",
      "title": "Admission Notice for HS 1st Year students Science & Arts Stream",
      "url": "https://pduamamjonga.ac.in/files/6256-20250422210139.pdf",
      "hash": "95296db11370f67b9a2014695c92f022caa0379e8202d9f41035719bec01a861",
      "detected_at": "2026-05-18T17:57:15.298Z"
    },
    {
      "date": "2025-04-13",
      "title": "Notification for HS 1st Year Students",
      "url": "https://pduamamjonga.ac.in/files/2561-20250422205907.pdf",
      "hash": "2c5e8070ff7803b7c4b3fa5a58f05deb0365b0b4b6f29ff16ad3442095bbae89",
      "detected_at": "2026-05-18T17:57:15.298Z"
    },
    {
      "date": "2025-04-12",
      "title": "Notice for UG Samarth Admission Session 2025-26",
      "url": "https://pduamamjonga.ac.in/files/5328-20250422211523.pdf",
      "hash": "729129e1862e0d8eddb97735c69b8ade64cdca163ebc43e545871252f02de3f8",
      "detected_at": "2026-05-18T17:57:15.298Z"
    },
    {
      "date": "2025-04-11",
      "title": "Examination form fill up notice",
      "url": "https://pduamamjonga.ac.in/files/6952-20250412142855.pdf",
      "hash": "6b59854abca684f346c4520693eba904da20a3920200bc9bd63b1c640db20386",
      "detected_at": "2026-05-18T17:57:15.298Z"
    },
    {
      "date": "2025-04-09",
      "title": "Programs for Sessional Examination 2024-25",
      "url": "https://pduamamjonga.ac.in/files/3067-20250412143535.pdf",
      "hash": "5736b1e86e5ff8aa973280b55c88904b485c71fb301516c22b6e1c7dd04603b2",
      "detected_at": "2026-05-18T17:57:15.298Z"
    },
    {
      "date": "2025-04-04",
      "title": "Notice for HS 1st Year students (Science & Arts)",
      "url": "https://pduamamjonga.ac.in/files/3896-20250405120023.pdf",
      "hash": "f40c837a0df775fa051f79bcbfb9702ecaccc55e35b801588915934dfff1bd6d",
      "detected_at": "2026-05-18T17:57:15.298Z"
    },
    {
      "date": "2025-04-04",
      "title": "Notification for HS 1st Year students",
      "url": "https://pduamamjonga.ac.in/files/6758-20250405115258.pdf",
      "hash": "191efe6dfcea3be71ae3cd4892347cfd87fd4eb7ed23b47ec2f5ff34145ce3ec",
      "detected_at": "2026-05-18T17:57:15.298Z"
    },
    {
      "date": "2025-03-29",
      "title": "Programme for BA/B.Sc. 6th semester Exam.2025",
      "url": "https://pduamamjonga.ac.in/files/7211-20250405114944.pdf",
      "hash": "e822880ebfc9a2190aa41603f5ccfc58993fb6d188941a901633bc9dbd6b0beb",
      "detected_at": "2026-05-18T17:57:15.298Z"
    },
    {
      "date": "2025-03-29",
      "title": "Notice for BA/B.Sc. 2nd Semester Exam. 2025",
      "url": "https://pduamamjonga.ac.in/files/5258-20250405114758.pdf",
      "hash": "ff40b8c8bc6f2f5d268299c615881fc48d333c01ffaf93a030e1b24624e2324d",
      "detected_at": "2026-05-18T17:57:15.298Z"
    },
    {
      "date": "2025-03-22",
      "title": "ORDER Copy of Cancellation of HS First Year Examination 2025",
      "url": "https://pduamamjonga.ac.in/files/4434-20250323203506.pdf",
      "hash": "441a17126cd9df5f159fb0884737197d007954fb10e6a4f57bcda4e4ec75dcb9",
      "detected_at": "2026-05-18T17:57:15.298Z"
    },
    {
      "date": "2025-03-20",
      "title": "Notice for HS 1ST Year students",
      "url": "https://pduamamjonga.ac.in/files/7541-20250323203225.pdf",
      "hash": "358283242900aa239807157dc2a519a6f54ff77e3f3bd6fbef24d82d705ece8b",
      "detected_at": "2026-05-18T17:57:15.298Z"
    },
    {
      "date": "2025-01-23",
      "title": "Programme for H.S Final Year Examination-2025",
      "url": "https://pduamamjonga.ac.in/files/6340-20250127215005.pdf",
      "hash": "25ab0b97f533a7112a2710171a186a047c0dad9918cd74c3f9dd87f1725eff7b",
      "detected_at": "2026-05-18T17:57:15.298Z"
    },
    {
      "date": "2025-01-23",
      "title": "H.S Final Practical Examination, Program,2025",
      "url": "https://pduamamjonga.ac.in/files/5926-20250127214828.pdf",
      "hash": "b375cdffa3983b36b16e5505ce06c94a91fc7f6215addbd5d1266ee3c9880660",
      "detected_at": "2026-05-18T17:57:15.298Z"
    },
    {
      "date": "2024-11-14",
      "title": "Notice General Election of Students' Union, PDUAM, Amjonga",
      "url": "https://pduamamjonga.ac.in/files/9538-20241116114610.pdf",
      "hash": "189cb5dfbe94ee1cc849d25d3ad0d2f9f88b75c27f58a9d9d44f8329311d8d91",
      "detected_at": "2026-05-18T17:57:15.298Z"
    },
    {
      "date": "2024-11-09",
      "title": "Form Fill Up Notice regarding HS Final Examination 2025 (Science & Arts)",
      "url": "https://pduamamjonga.ac.in/files/8819-20241109121358.pdf",
      "hash": "87e0e0970b4bc02440307691fb6926ad0bd6d4f3232d21d405c107fac9fb499b",
      "detected_at": "2026-05-18T17:57:15.298Z"
    },
    {
      "date": "2024-09-24",
      "title": "Notification for Final Spot Admission, Academic Session 2024",
      "url": "https://pduamamjonga.ac.in/files/9338-20240925122221.pdf",
      "hash": "f9b3523a945ba18945a11be1a3e04962b185f9e7f0ef8fd3d65fc17986946c0f",
      "detected_at": "2026-05-18T17:57:15.298Z"
    },
    {
      "date": "2024-09-16",
      "title": "Programs for Sessional/ Internal examinations 2024-25",
      "url": "https://pduamamjonga.ac.in/files/6068-20240919123931.pdf",
      "hash": "da50b0c74314130cc24fa0e8177a529010eef61ad99c9871fc12a283d6cab9d4",
      "detected_at": "2026-05-18T17:57:15.298Z"
    },
    {
      "date": "2024-09-16",
      "title": "Logo & Motto Design Competition for Eco Club",
      "url": "https://pduamamjonga.ac.in/files/8664-20240919123225.jpg",
      "hash": "5e0dac28d5c96491d26e4b741c6887661b573e82c290d32e1b3841f651a6eec5",
      "detected_at": "2026-05-18T17:57:15.298Z"
    },
    {
      "date": "2024-09-12",
      "title": "SOP Regarding the Sessional/ Internal Examination 2024",
      "url": "https://pduamamjonga.ac.in/files/9786-20240919123434.pdf",
      "hash": "709e4fc0e0b9a222e536287cf0e025c6c012d84eb90fa95ddff8cc0749d504ad",
      "detected_at": "2026-05-18T17:57:15.298Z"
    },
    {
      "date": "2024-08-21",
      "title": "Tender Result Notice",
      "url": "https://pduamamjonga.ac.in/files/7164-20240821170556.pdf",
      "hash": "cb7101af79810dc4dbc386e8c2770374addec2584286284d468478ed39e6cd23",
      "detected_at": "2026-05-18T17:57:15.298Z"
    },
    {
      "date": "2024-08-21",
      "title": "Notice for College canteen",
      "url": "https://pduamamjonga.ac.in/files/4898-20240821170445.pdf",
      "hash": "8d8256cb2d9dadca0b9acea79f9a4150a0e6547e55be355fc97983e546894d0a",
      "detected_at": "2026-05-18T17:57:15.298Z"
    },
    {
      "date": "2024-08-19",
      "title": "Notice for Final Spot Admission in to BA/B.Sc.(FYUGP) 1st Semester",
      "url": "https://pduamamjonga.ac.in/files/8553-20240819111040.pdf",
      "hash": "9a3b044d79ac69a94692cebbfb578c3e2a82bb960db5d9db66b7a8b9c6060979",
      "detected_at": "2026-05-18T17:57:15.298Z"
    },
    {
      "date": "2024-08-14",
      "title": "Post -Matric Scholarship for SC & OBC Students",
      "url": "https://pduamamjonga.ac.in/files/7058-20240814154222.pdf",
      "hash": "940844450a052056a6ad0441a43eedbc654f186efedf335c0ba602f1d60289f0",
      "detected_at": "2026-05-18T17:57:15.298Z"
    },
    {
      "date": "2024-08-14",
      "title": "Notice for 78th INDEPENDENCE DAY",
      "url": "https://pduamamjonga.ac.in/files/8818-20240814153853.pdf",
      "hash": "31bdacf0f6caaacb8a80898c7e8203c43f3e4a629bdde99a50edda36cadc023e",
      "detected_at": "2026-05-18T17:57:15.298Z"
    },
    {
      "date": "2024-08-12",
      "title": "Tender Application Form",
      "url": "https://pduamamjonga.ac.in/files/2793-20240814115017.pdf",
      "hash": "1376694315a978ebb2c5e8aa91ea203905e7608e3babe07a79dc6cc83dd79bd8",
      "detected_at": "2026-05-18T17:57:15.298Z"
    },
    {
      "date": "2024-08-12",
      "title": "Tender Notice",
      "url": "https://pduamamjonga.ac.in/files/9512-20240813104950.pdf",
      "hash": "92ce1d3db3d5f5fffd2f8fb82402d1e4c628ffe54e8c4d6b55eea2481d8edd39",
      "detected_at": "2026-05-18T17:57:15.298Z"
    },
    {
      "date": "2024-07-30",
      "title": "Notification for regular class of Higher Secondary 1st Year (Science & Arts), 2nd Year (Science & Arts), B.A/B.Sc.- 3rd Semester B.A/B.Sc.- 5th Semester",
      "url": "https://pduamamjonga.ac.in/files/6189-20240731105244.pdf",
      "hash": "866645fef873459f413e2918bf6d267f807112ef2d413672f0880efa40f36532",
      "detected_at": "2026-05-18T17:57:15.298Z"
    },
    {
      "date": "2024-07-29",
      "title": "Notice Regarding Free Book Distribution for the students of HS First Year Students (Art & Science) 2024-25",
      "url": "https://pduamamjonga.ac.in/files/4709-20240730135314.pdf",
      "hash": "4f674cfb5c3a3c158f9f0780dd842ef7ae1ebbdca71de929d6832ba27cca7825",
      "detected_at": "2026-05-18T17:57:15.298Z"
    },
    {
      "date": "2024-07-29",
      "title": "HS Second Year Admission for the Session 2024-25",
      "url": "https://pduamamjonga.ac.in/files/4921-20240730135141.pdf",
      "hash": "19011fa6a937aef9647bd68aad1c4b3a57124f33c493a017bb8c086483aa9ae0",
      "detected_at": "2026-05-18T17:57:15.298Z"
    },
    {
      "date": "2024-07-08",
      "title": "Notice for B.A/B.Sc. 1st Semester Students",
      "url": "https://pduamamjonga.ac.in/files/1466-20240709115707.pdf",
      "hash": "2136a7bd3166cc27fa024e1888e77e28199126f197cc9a5a2133325256c599f2",
      "detected_at": "2026-05-18T17:57:15.298Z"
    },
    {
      "date": "2024-06-24",
      "title": "2nd Merit List for B.Sc. 1st Semester (FYUGP) (Science Stream ) Date of Admission :26th Jun to 28th Jun, 2024",
      "url": "https://pduamamjonga.ac.in/files/2950-20240625145400.pdf",
      "hash": "427d32909cddd673bda33dc271b9525f5244144a5296b64a70f630aa704f4206",
      "detected_at": "2026-05-18T17:57:15.298Z"
    },
    {
      "date": "2024-06-24",
      "title": "2nd Merit List for B.A. 1st Semester (FYUGP) (Arts Stream ) Date of Admission :26th Jun to 28th Jun, 2024",
      "url": "https://pduamamjonga.ac.in/files/3469-20240625145146.pdf",
      "hash": "9a0f1af7cd888df30d9e7b9c1390488bf4060739c70cabf4f5c38ca7c0a89e0e",
      "detected_at": "2026-05-18T17:57:15.298Z"
    },
    {
      "date": "2024-06-20",
      "title": "Admission Notice",
      "url": "https://pduamamjonga.ac.in/files/7094-20240620105842.pdf",
      "hash": "32194e3372b9036f315a2551c1c2d943f6ae6c3416129d94484362a6cca3c5f1",
      "detected_at": "2026-05-18T17:57:15.298Z"
    },
    {
      "date": "2024-06-19",
      "title": "1st Merit List for B.A. 1st Semester (FYUGP) (Arts Stream )",
      "url": "https://pduamamjonga.ac.in/files/7913-20240619155840.pdf",
      "hash": "a8175a9b27ed2e9a8855c8df3813279226fddd220577e789c55593491e36f276",
      "detected_at": "2026-05-18T17:57:15.298Z"
    },
    {
      "date": "2024-06-19",
      "title": "1st Merit List for B.Sc. 1st Semester (FYUGP) (Science Stream )",
      "url": "https://pduamamjonga.ac.in/files/3028-20240619155648.pdf",
      "hash": "1230e6459eab2307f92c0e252a983b20ab9f37ebd22abeb8a51197f0e4f678a7",
      "detected_at": "2026-05-18T17:57:15.298Z"
    },
    {
      "date": "2024-06-12",
      "title": "B.A./B.Sc. First Semester Admission Notice for the academic year 2024-25",
      "url": "https://pduamamjonga.ac.in/files/8158-20240612140917.pdf",
      "hash": "8c891c451d50c8dee6afd38874f420296253bbc893023e5066245612f8c78e3c",
      "detected_at": "2026-05-18T17:57:15.298Z"
    },
    {
      "date": "2024-05-29",
      "title": "Notice for B.Sc 6th semester Practical examination and Project Presentation,2024",
      "url": "https://pduamamjonga.ac.in/files/2608-20240531164254.jpg",
      "hash": "bb1a88f412cbca90358e173d7d90d35033222e41de7d8f6f9a23a77876e0d844",
      "detected_at": "2026-05-18T17:57:15.298Z"
    },
    {
      "date": "2024-05-28",
      "title": "Admission Notice for B.A. / B.Sc. First Semester (FYUGP) for the academic session 2024-2025",
      "url": "https://pduamamjonga.ac.in/files/3782-20240601125753.pdf",
      "hash": "b1ee895d04eacf57ddae856bf439b8841966fb56984f8e39951efc71f7d8d358",
      "detected_at": "2026-05-18T17:57:15.298Z"
    },
    {
      "date": "2024-05-17",
      "title": "Form Fill Up- FYUGP 2nd Semester 2024",
      "url": "https://pduamamjonga.ac.in/files/6816-20240517112324.pdf",
      "hash": "ee44c5db37153f3e2a6265f093e55e23e0a0478e149a0a0861c56819b2aa868a",
      "detected_at": "2026-05-18T17:57:15.298Z"
    },
    {
      "date": "2024-05-08",
      "title": "Programme of B.Sc. 6th Semester (CBCS) Examination, 2024",
      "url": "https://pduamamjonga.ac.in/files/1598-20240508133518.pdf",
      "hash": "90b19333e4cd7ab1ad36da6899f52525bec536ca42140a575885c813a8165ab6",
      "detected_at": "2026-05-18T17:57:15.298Z"
    },
    {
      "date": "2024-05-08",
      "title": "Programme of B.Sc.4th Semester (CBCS) Examination, 2024",
      "url": "https://pduamamjonga.ac.in/files/7504-20240508133328.pdf",
      "hash": "1869360a396de59197649e5edcd3ee3077c6cbb0aad6031712da427127888999",
      "detected_at": "2026-05-18T17:57:15.298Z"
    },
    {
      "date": "2024-05-08",
      "title": "Programme of B.A./B.Sc. 2nd Semester (CBCS) Examination, 2024",
      "url": "https://pduamamjonga.ac.in/files/3876-20240508133205.pdf",
      "hash": "845ac3f8f2686b4fc57e384fe2d734feb8549b88bf0cd96c74d8973c200fd67e",
      "detected_at": "2026-05-18T17:57:15.298Z"
    },
    {
      "date": "2024-05-06",
      "title": "Provisional Merit List cum Admission Notice for Higher Secondary First Year (Arts) for academic year 2024-25",
      "url": "https://pduamamjonga.ac.in/files/8549-20240506143236.pdf",
      "hash": "b89c1fa934b06a13d3803bb3501622d6465daaed254e1f19d4a528e597b1a3db",
      "detected_at": "2026-05-18T17:57:15.298Z"
    },
    {
      "date": "2024-05-06",
      "title": "Provisional Merit List cum Admission Notice for Higher Secondary First Year (Science) for academic year 2024-25",
      "url": "https://pduamamjonga.ac.in/files/7392-20240506142924.pdf",
      "hash": "24b9a68af0c685b982bdcaf4d8b44854b63d6b777c6cc9add5b19c4fba85e262",
      "detected_at": "2026-05-18T17:57:15.298Z"
    },
    {
      "date": "2024-04-24",
      "title": "উচ্চতৰ মাধ্যমিক প্ৰথম বৰ্ষ (২০২৪-২০২৫ ইং শিক্ষা বৰ্ষ) নামভৰ্তি জাননী",
      "url": "https://pduamamjonga.ac.in/files/8361-20240426150543.pdf",
      "hash": "315d597ad2a30e60c95f85b91d61c39abd56db1106e3391bddbb047c0099028c",
      "detected_at": "2026-05-18T17:57:15.298Z"
    },
    {
      "date": "2024-04-24",
      "title": "Admission Notice of Higher Secondary First Year 2024-25 (Science & Arts)",
      "url": "https://pduamamjonga.ac.in/files/6143-20240426150109.pdf",
      "hash": "c88898e14094d6afe4da1a02d930949d3f6c626bc4abce5c518dd357705ac569",
      "detected_at": "2026-05-18T17:57:15.298Z"
    },
    {
      "date": "2024-04-20",
      "title": "Notice inviting Tender for Staff Canteen under PDUAM, Amjonga",
      "url": "https://pduamamjonga.ac.in/files/7378-20240423134120.pdf",
      "hash": "ad46a0fa68bb5bbef7cea3606dfd71f31c6967857323c8b8685288b6795d387c",
      "detected_at": "2026-05-18T17:57:15.298Z"
    },
    {
      "date": "2024-04-20",
      "title": "Notice for HS 1st Year Students",
      "url": "https://pduamamjonga.ac.in/files/4313-20240420171411.pdf",
      "hash": "282f5f5eba68223e356251e488ba5c210e2a28b5313d32c28523f8503b6f2780",
      "detected_at": "2026-05-18T17:57:15.298Z"
    },
    {
      "date": "2024-04-06",
      "title": "Notice Programs for Sessional Examinations 2023-24 (Even Semester)",
      "url": "https://pduamamjonga.ac.in/files/1352-20240416141730.pdf",
      "hash": "6fe7eec5b4fbcb0fb3e297e984973a94178453b155d3a3217804b68b4f39c0b4",
      "detected_at": "2026-05-18T17:57:15.298Z"
    },
    {
      "date": "2024-04-05",
      "title": "Notice inviting Tender for Staff Canteen under PDUAM, Amjonga",
      "url": "https://pduamamjonga.ac.in/files/8794-20240405151342.pdf",
      "hash": "ccda4bd8d0a89fdebd44c110977ef90d72867c3d9c592c2dbca7c34939ab455f",
      "detected_at": "2026-05-18T17:57:15.298Z"
    },
    {
      "date": "2024-03-21",
      "title": "Local Holiday on account of Dol Jatra (Holi) No: GPE.19/2006/Pt-1/91",
      "url": "https://pduamamjonga.ac.in/files/5137-20240322092604.jpg",
      "hash": "b56a1799d74d406f6c53f15ec688244f5daddc1efdacfc1c2ab25d968fddc3af",
      "detected_at": "2026-05-18T17:57:15.298Z"
    },
    {
      "date": "2024-03-19",
      "title": "Matter relating to leave of officers/staff No: GPE 28/2023/119",
      "url": "https://pduamamjonga.ac.in/files/4627-20240322092322.pdf",
      "hash": "d8d55b9098265a7545374a35cef5453174b0d7412687a2cdba73c8ced8616943",
      "detected_at": "2026-05-18T17:57:15.298Z"
    },
    {
      "date": "2024-01-24",
      "title": "Notification for 8th Annual College Week-2024",
      "url": "https://pduamamjonga.ac.in/files/5088-20240204122639.pdf",
      "hash": "97cd02f02c3fa4677c07c9ffdf6581aa82092c1a90d78cb5534c5c54eda5b944",
      "detected_at": "2026-05-18T17:57:15.298Z"
    },
    {
      "date": "2024-01-20",
      "title": "Notification for HS Final Year Practical Examination 2024",
      "url": "https://pduamamjonga.ac.in/files/8093-20240204122413.pdf",
      "hash": "25448b0ec5fc06d40a0fb2d20e270ea4846ad9e945689071895ba0acbaa89f11",
      "detected_at": "2026-05-18T17:57:15.298Z"
    },
    {
      "date": "2023-11-09",
      "title": "Notice for B.Sc. 5th Semester Examination 2023",
      "url": "https://pduamamjonga.ac.in/files/3142-20231118121034.pdf",
      "hash": "9d2ba6bac944eb836bfac16704c99232857f00d974174f59b38a2141f55f57c4",
      "detected_at": "2026-05-18T17:57:15.298Z"
    },
    {
      "date": "2023-11-09",
      "title": "Notice for B.Sc. 1st Semester & 3rd Semester Examination 2023",
      "url": "https://pduamamjonga.ac.in/files/2241-20231118120954.pdf",
      "hash": "d76e213995e058f59f0a4c892b6196639e8d1e11a8ee410dc9152b626ccae9b8",
      "detected_at": "2026-05-18T17:57:15.298Z"
    },
    {
      "date": "2023-09-30",
      "title": "Notice for General Election of the Students Union for the academic session 2023-24 of PDUAM, Amjonga,",
      "url": "https://pduamamjonga.ac.in/files/8180-20230930132116.pdf",
      "hash": "37660fcb157c039caeaf3f53f8d1525b84c684a3805c45d3ca1c0ee6ceaa2fe7",
      "detected_at": "2026-05-18T17:57:15.298Z"
    },
    {
      "date": "2023-09-04",
      "title": "Code of conduct for Students Union Election-2023-24",
      "url": "https://pduamamjonga.ac.in/files/9195-20231004085146.pdf",
      "hash": "4be825528e9142bfc4a6ad31c188b6b6ca657368e61b09ffeab67fc3c5fee2f6",
      "detected_at": "2026-05-18T17:57:15.298Z"
    },
    {
      "date": "2023-09-04",
      "title": "Code of conduct for Students Union Election-2023-24",
      "url": "https://pduamamjonga.ac.in/files/2319-20231004085122.pdf",
      "hash": "01b3ea16f7354cba48837b61e4ab933cd43bf08190718cddf57a19aedef4d0a1",
      "detected_at": "2026-05-18T17:57:15.298Z"
    },
    {
      "date": "2023-09-04",
      "title": "Notification for Students Union Election-2023-24",
      "url": "https://pduamamjonga.ac.in/files/9761-20231004085014.pdf",
      "hash": "1fe26ccbdd1507f258dbc880a217b7e3c4da8ae537cec3d920b9b4dc64329b6d",
      "detected_at": "2026-05-18T17:57:15.298Z"
    },
    {
      "date": "2023-08-28",
      "title": "Selection list for the Post of Assistant Professor in the Department of Political Science, PDUAM, Amjonga",
      "url": "https://pduamamjonga.ac.in/files/5168-20230828190527.pdf",
      "hash": "bca302288d6b287418774886165ef2f58273f57088d5ff6d423e98f40ca7f9a8",
      "detected_at": "2026-05-18T17:57:15.298Z"
    },
    {
      "date": "2023-08-28",
      "title": "Rejection list for the Post of Assistant Professor in the Department of Political Science, PDUAM, Amjonga",
      "url": "https://pduamamjonga.ac.in/files/6911-20230828190352.pdf",
      "hash": "4d6a61955a5636da514c84e03c18a37ff0006f0c112eaf3af35e8c98ba1c2b26",
      "detected_at": "2026-05-18T17:57:15.298Z"
    },
    {
      "date": "2023-08-26",
      "title": "Selection list for the Post of Assistant Professor in the Department of Sociology, PDUAM, Amjonga",
      "url": "https://pduamamjonga.ac.in/files/4182-20230828174943.pdf",
      "hash": "bf4d1f495dce94ca43b8c493440781e594020b860ffce538a1777fa131f6be2e",
      "detected_at": "2026-05-18T17:57:15.298Z"
    },
    {
      "date": "2023-08-26",
      "title": "Rejection list for the Post of Assistant Professor in the Department of Sociology, PDUAM, Amjonga",
      "url": "https://pduamamjonga.ac.in/files/7696-20230826181009.pdf",
      "hash": "db9fa04f1f296e176dee88cdefcd8ff9e66668c37b7f31afa2f32440df816dc6",
      "detected_at": "2026-05-18T17:57:15.298Z"
    },
    {
      "date": "2023-08-25",
      "title": "Rejection list for the Post of Assistant Professor of the Department of Education, PDUAM, Amjonga",
      "url": "https://pduamamjonga.ac.in/files/2048-20230825192952.pdf",
      "hash": "4c987a6d4558ce89d535ad0a86b692b18e27565da870dadc0701e053d61420d4",
      "detected_at": "2026-05-18T17:57:15.298Z"
    },
    {
      "date": "2023-08-25",
      "title": "Selection list for the Post of Assistant Professor of the Department of Education, PDUAM, Amjonga",
      "url": "https://pduamamjonga.ac.in/files/6007-20230825192920.pdf",
      "hash": "63a2be18f4142c8db785236b267234772430fa1ce015ad43898ae4da0fe0ed4a",
      "detected_at": "2026-05-18T17:57:15.298Z"
    },
    {
      "date": "2023-08-24",
      "title": "Selection list for the Post of Assistant Professor of the Department of History, PDUAM, Amjonga",
      "url": "https://pduamamjonga.ac.in/files/7505-20230824155633.pdf",
      "hash": "dac8970c01b66f6a4fbb235b4111148d9f3d6d22b7ddb4c611d188bc643da713",
      "detected_at": "2026-05-18T17:57:15.298Z"
    },
    {
      "date": "2023-08-18",
      "title": "Reject list for the Department of Economics, PDUAM,Amjonga",
      "url": "https://pduamamjonga.ac.in/files/6928-20230818190603.pdf",
      "hash": "e04179c5fac99d689b1fb2dc59161646584f2a4a36b95684d53e871c3aedabe9",
      "detected_at": "2026-05-18T17:57:15.298Z"
    },
    {
      "date": "2023-08-18",
      "title": "Selection list for the Post of Assistant Professor of the Department of Economics, PDUAM, Amjonga",
      "url": "https://pduamamjonga.ac.in/files/2054-20230818190058.pdf",
      "hash": "f0d96cf5a1cdbb16b8be545810a770940ab9a098922096efae50da37bab083e6",
      "detected_at": "2026-05-18T17:57:15.298Z"
    },
    {
      "date": "2023-08-12",
      "title": "Selection list for the Post of Assistant Professor of the Department of Computer Science",
      "url": "https://pduamamjonga.ac.in/files/6255-20230815122654.pdf",
      "hash": "620abdb6a76558b6dc78117624bcb3074efc0ea52f775ae9f569cba07affe6d1",
      "detected_at": "2026-05-18T17:57:15.298Z"
    },
    {
      "date": "2023-08-11",
      "title": "List of Received Applications for the Arts Stream of PDUAM, Amjonga",
      "url": "https://pduamamjonga.ac.in/files/8627-20230811195214.pdf",
      "hash": "79c11660538ccf618255da5e0dfec69558c84c181790934ec35afa93343023cd",
      "detected_at": "2026-05-18T17:57:15.298Z"
    },
    {
      "date": "2023-08-11",
      "title": "Selection list for the Post of Assistant Professor of the Department of Mathematics",
      "url": "https://pduamamjonga.ac.in/files/8132-20230811194958.pdf",
      "hash": "5c0c1a11d960b0ddf5a71befda1451579903880ea58160f3c6f273b018ebd243",
      "detected_at": "2026-05-18T17:57:15.298Z"
    },
    {
      "date": "2023-08-11",
      "title": "Selection list for the Post of Assistant Professor of the Department of Zoology",
      "url": "https://pduamamjonga.ac.in/files/4978-20230811194928.pdf",
      "hash": "22dd17c4aadaa7780dd9609858ea05dce0d39ca01b85916cdb4eb773c58ad09b",
      "detected_at": "2026-05-18T17:57:15.298Z"
    },
    {
      "date": "2023-08-11",
      "title": "Selection list for the Post of Assistant Professor of the Department of English",
      "url": "https://pduamamjonga.ac.in/files/6040-20230811194858.pdf",
      "hash": "58fcfd4a7d41737b3c79b99e4854f605b23ef5145c566f339bfc9df69152b886",
      "detected_at": "2026-05-18T17:57:15.298Z"
    },
    {
      "date": "2023-08-11",
      "title": "Under Taking Form for the Post of Assistant Professors, PDUAM, Amjonga",
      "url": "https://pduamamjonga.ac.in/files/1921-20230811194714.pdf",
      "hash": "e833569f856f04cfd285e9ff5cc0409128dc3fa3c61442841426a6063c1441b6",
      "detected_at": "2026-05-18T17:57:15.298Z"
    },
    {
      "date": "2023-08-08",
      "title": "Merit List Cum Admission Notice for BA First Semester (2023-24)",
      "url": "https://pduamamjonga.ac.in/files/1793-20230809104007.pdf",
      "hash": "29916ad44ff5f8810c270cd04b39ce70ed1d4a784431b637dd848941d7111997",
      "detected_at": "2026-05-18T17:57:15.298Z"
    },
    {
      "date": "2023-08-05",
      "title": "Merit List Cum Admission Notice of HS First Year-Arts (2023-2024)",
      "url": "https://pduamamjonga.ac.in/files/8045-20230808171901.pdf",
      "hash": "7ecb58f435de2febd40017a32275e85c16d0889a0a8d2b5ba5935b428dadd1af",
      "detected_at": "2026-05-18T17:57:15.298Z"
    },
    {
      "date": "2023-07-29",
      "title": "Biometric Timing",
      "url": "https://pduamamjonga.ac.in/files/4816-20230729124747.pdf",
      "hash": "9baaf6fdd5a5625efef03800dfa04f98d9675f706a47e3e64786dabeb2f33af4",
      "detected_at": "2026-05-18T17:57:15.298Z"
    },
    {
      "date": "2023-07-28",
      "title": "Admission Notice for Arts Stream, PDUAM, Amjonga",
      "url": "https://pduamamjonga.ac.in/files/9231-20230728142646.pdf",
      "hash": "5e9a462c51dc4ebd64b3d04bf39dd3ed451d0b5c0816edfe4e8c56a273db68fd",
      "detected_at": "2026-05-18T17:57:15.298Z"
    },
    {
      "date": "2023-07-28",
      "title": "Notification For the Teaching & Non-Teaching Staff, PDUAm,Amjonga",
      "url": "https://pduamamjonga.ac.in/files/2081-20230728142548.pdf",
      "hash": "3ad3de3beb98f3976dd455951645d12bc7714ae9090058da232d91572c09c989",
      "detected_at": "2026-05-18T17:57:15.298Z"
    },
    {
      "date": "2023-07-28",
      "title": "Applications received for the Post of Assistant Professors in the Deptt. of English, Computer Science, Mathematics & Zoology PDUAM, Amjonga",
      "url": "https://pduamamjonga.ac.in/files/7863-20230728142411.pdf",
      "hash": "3676c2956da6f7458d9f37827641ca0d88fb098091369a0a74c7b9bbc42da47e",
      "detected_at": "2026-05-18T17:57:15.298Z"
    },
    {
      "date": "2023-07-20",
      "title": "Recruitment of the Assistant Professor for Arts Stream-2023",
      "url": "https://pduamamjonga.ac.in/files/1490-20230720111755.pdf",
      "hash": "5590265f6f6372963daa4cc22829e8495a0f37929e0889b0ac5feb0064529aaa",
      "detected_at": "2026-05-18T17:57:15.298Z"
    },
    {
      "date": "2023-07-19",
      "title": "Opening of Samarth Esuit portal for admission into B.Sc. First Semester Classes (2023-24)",
      "url": "https://pduamamjonga.ac.in/files/2334-20230720093712.pdf",
      "hash": "6f1562f36643eeb0f603300b7af11ee80e4db5aa78684395bf6cf8294439011e",
      "detected_at": "2026-05-18T17:57:15.298Z"
    },
    {
      "date": "2023-07-15",
      "title": "Second Merit List of B.Sc. First Semester (2023-24) and Admission Date Notification",
      "url": "https://pduamamjonga.ac.in/files/2013-20230715120119.pdf",
      "hash": "65e426ed15dd22aa572492ee26a84f490095ac35ec536a98e858cd81f16fc8fe",
      "detected_at": "2026-05-18T17:57:15.298Z"
    },
    {
      "date": "2023-07-09",
      "title": "Application Form for recruitment of Assistant Professor",
      "url": "https://pduamamjonga.ac.in/files/2119-20230714112233.pdf",
      "hash": "6bf5051c2a6bc22fe7f3f7f97a943af960149557be42a1dee308c3a96bea5828",
      "detected_at": "2026-05-18T17:57:15.298Z"
    },
    {
      "date": "2023-07-09",
      "title": "Notice for recruitment of Assistant Professor",
      "url": "https://pduamamjonga.ac.in/files/5504-20230712110638.pdf",
      "hash": "7c7893576fbb6aee0564d0f11a8c4c6d85fdb1c6b87f3ce0c199103d1c6df054",
      "detected_at": "2026-05-18T17:57:15.298Z"
    },
    {
      "date": "2023-07-07",
      "title": "Admission Notice and Merit List for B.Sc First Semester (2023-2024)",
      "url": "https://pduamamjonga.ac.in/files/8899-20230711144902.pdf",
      "hash": "202934d241e6782028529bbfe63d80c47c55a87a26e42865c6500b97104ea5d3",
      "detected_at": "2026-05-18T17:57:15.298Z"
    },
    {
      "date": "2023-06-23",
      "title": "Admission Notice for HS First Year (2023-2024)",
      "url": "https://pduamamjonga.ac.in/files/3018-20230623155929.pdf",
      "hash": "236c9b26c0a0ff1e2e8ec4232be835cb3f2364b839137b894f5ba8f04acc7a88",
      "detected_at": "2026-05-18T17:57:15.298Z"
    },
    {
      "date": "2023-06-20",
      "title": "Notice",
      "url": "https://pduamamjonga.ac.in/files/5105-20230621100353.pdf",
      "hash": "76056f7b2f014cea06c634d62265d62342758aca925a432f5bd64a809bc3d3be",
      "detected_at": "2026-05-18T17:57:15.298Z"
    },
    {
      "date": "2023-06-16",
      "title": "Pre-Admission Notice for B.Sc. First semester (Merit List-1)",
      "url": "https://pduamamjonga.ac.in/files/2184-20230616135456.pdf",
      "hash": "ddeae2bdbe812d0f96b6ec357d148829b47493d06e268cfdff9a136588c31f4f",
      "detected_at": "2026-05-18T17:57:15.298Z"
    },
    {
      "date": "2023-06-12",
      "title": "Admission Notice",
      "url": "https://pduamamjonga.ac.in/files/3356-20230612173929.pdf",
      "hash": "978b8b2cb98c6893f319534d3d5fe098dd207bac750cc59bb564ff3ade748777",
      "detected_at": "2026-05-18T17:57:15.298Z"
    },
    {
      "date": "2023-06-10",
      "title": "Merit List of Higher Secondary First Year (Science) for the Session 2023-24",
      "url": "https://pduamamjonga.ac.in/files/7284-20230610155900.pdf",
      "hash": "fe8fd49b8a09debc0dd9b09cb3f75891eccccdda30ec3275ea16106982fa18cb",
      "detected_at": "2026-05-18T17:57:15.298Z"
    },
    {
      "date": "2023-06-01",
      "title": "Notice for B.Sc. 3rd Sem Admission",
      "url": "https://pduamamjonga.ac.in/files/6917-20230601170516.pdf",
      "hash": "fb2634c5a5a2bba21c57528236e51c83a7ba7802e5a2f25d0ad8e77ab142bf4f",
      "detected_at": "2026-05-18T17:57:15.298Z"
    },
    {
      "date": "2023-06-01",
      "title": "Notice for B.Sc. Admission",
      "url": "https://pduamamjonga.ac.in/files/1614-20230601170429.pdf",
      "hash": "97ef3cfb7f8af21c455111879233f87f98acd2f94b6fd1d0f4e9a2ef4ba5122d",
      "detected_at": "2026-05-18T17:57:15.298Z"
    },
    {
      "date": "2023-06-01",
      "title": "Notice for Higher Secondary 1st Year2023",
      "url": "https://pduamamjonga.ac.in/files/4078-20230601170329.pdf",
      "hash": "14a21b7089f6baf1a479185def2098c5af493b878233381d0850abbff44e4963",
      "detected_at": "2026-05-18T17:57:15.298Z"
    },
    {
      "date": "2023-05-26",
      "title": "Notification for Higher Secondary1st Year Admission( Science)",
      "url": "https://pduamamjonga.ac.in/files/6811-20230527104032.pdf",
      "hash": "1768da89d5136d4809f9fde9b298f1f59a2596e3a48aa95b4c510d0a32333aad",
      "detected_at": "2026-05-18T17:57:15.298Z"
    },
    {
      "date": "2023-03-29",
      "title": "Exam Programme B.Sc Second Sem, 2023",
      "url": "https://pduamamjonga.ac.in/files/1309-20230329163157.pdf",
      "hash": "1ba9fc8ba3878fd22184639d53ce8aacadb22a94abf97672c45ad5f39394b911",
      "detected_at": "2026-05-18T17:57:15.298Z"
    },
    {
      "date": "2023-03-29",
      "title": "Exam Programme B.Sc Fourth Sem, 2023",
      "url": "https://pduamamjonga.ac.in/files/2848-20230329163105.pdf",
      "hash": "b8f85ae8e0c5bf456de16f85b0892efbf13552c0ddbcd6fc4999810c6e0fc21f",
      "detected_at": "2026-05-18T17:57:15.298Z"
    },
    {
      "date": "2023-03-29",
      "title": "Exam Programme B.Sc Sixth Sem, 2023",
      "url": "https://pduamamjonga.ac.in/files/4007-20230329162957.pdf",
      "hash": "da9868654c0b02cc0b18be5a843994f68f3ea940defcc708c774acc71720bbe5",
      "detected_at": "2026-05-18T17:57:15.298Z"
    },
    {
      "date": "2023-03-25",
      "title": "Routine B.Sc 2nd Sem and 4th Sem",
      "url": "https://pduamamjonga.ac.in/files/5387-20230325140439.pdf",
      "hash": "81d5c5c4e78ced5fe3d3d005571fc07f58874e7854da7b7caf3a86bdb1f2d0ca",
      "detected_at": "2026-05-18T17:57:15.298Z"
    },
    {
      "date": "2023-03-25",
      "title": "H. S 1st Year routine practical examination,2023",
      "url": "https://pduamamjonga.ac.in/files/9054-20230325140117.pdf",
      "hash": "aaf143174d2ec4785e3cb739f4f30022c54bd9d0e347de33efe695d2111eec4b",
      "detected_at": "2026-05-18T17:57:15.298Z"
    },
    {
      "date": "2023-03-25",
      "title": "H.S 1st Year Practical Examination,2023",
      "url": "https://pduamamjonga.ac.in/files/5707-20230325140015.pdf",
      "hash": "50cd9ded093ae200778f7a6948c47440bbc0ff34c8f036688a7aab39e978a4a8",
      "detected_at": "2026-05-18T17:57:15.298Z"
    },
    {
      "date": "2023-01-28",
      "title": "Important Notice for H.S Final Year Exam-2023",
      "url": "https://pduamamjonga.ac.in/files/2522-20230128152710.pdf",
      "hash": "6b7f46ba8b8862e45610f2b96569f28468429e680bc83eee4fa0845f0ce409f7",
      "detected_at": "2026-05-18T17:57:15.298Z"
    },
    {
      "date": "2023-01-27",
      "title": "Higher Secondary Final Year Practical Examination Routine",
      "url": "https://pduamamjonga.ac.in/files/8277-20230127164939.pdf",
      "hash": "987fc5d32f6dc8562dbc477b7ddfa02e890b7f274dcf2ac6d7c21fb52c4bbc17",
      "detected_at": "2026-05-18T17:57:15.298Z"
    },
    {
      "date": "2023-01-25",
      "title": "Notice to all H.S 2nd Year Students",
      "url": "https://pduamamjonga.ac.in/files/4909-20230127092457.pdf",
      "hash": "c9b688c45e41d8019f17a50fee8a47980f2dea06f2174a2af89ca30dfca4ceed",
      "detected_at": "2026-05-18T17:57:15.298Z"
    },
    {
      "date": "2023-01-25",
      "title": "Notification for H.S 2nd Year Final Examination 2023",
      "url": "https://pduamamjonga.ac.in/files/8290-20230125150409.pdf",
      "hash": "1d6975e69cec8c5e66dd04d7510fa961f644ca8531c55e6b61de4b8d1e815121",
      "detected_at": "2026-05-18T17:57:15.298Z"
    },
    {
      "date": "2023-01-25",
      "title": "74th Republic Day",
      "url": "https://pduamamjonga.ac.in/files/8039-20230125140251.pdf",
      "hash": "968d8733c4b5a7cc8d7558bfba1a0db049a8b5d3cbf3a8d4e6efa1834c8922d2",
      "detected_at": "2026-05-18T17:57:15.298Z"
    },
    {
      "date": "2022-12-01",
      "title": "notice",
      "url": "https://pduamamjonga.ac.in/files/6362-20221201102557.docx",
      "hash": "b51cce213614aeb9bf0cc9b4e9ff1e397d1e00bdf8c5a695769b72517fed2a66",
      "detected_at": "2026-05-18T17:57:15.298Z"
    },
    {
      "date": "2022-11-30",
      "title": "Side Plan",
      "url": "https://pduamamjonga.ac.in/files/1420-20221130163357.pdf",
      "hash": "c149da1e861238062dd197200673821e857a76f67fb27b0844b829a84f0e1c51",
      "detected_at": "2026-05-18T17:57:15.298Z"
    },
    {
      "date": "2022-11-30",
      "title": "Notice",
      "url": "https://pduamamjonga.ac.in/files/7465-20221130135349.pdf",
      "hash": "3dd782f5659717801f8b169603249ab6017c98f5661872e7a791dc8a7bab5240",
      "detected_at": "2026-05-18T17:57:15.298Z"
    }
  ]
}